{
    "AX": {
        "error": 0.011739407457970556,
        "error_type": "SEM",
        "filter_outliers_dict": {
            "filter_outliers": true,
            "iterations": 1,
            "std_devs": 3,
            "use_iqr_filtering": false,
            "use_standard_deviation_filtering": false
        },
        "fit": "average",
        "fn": 24,
        "include_baseline_error": false,
        "n": 24,
        "outlier_excluded": [],
        "reviewed": true,
        "user_excluded": [],
        "value": -0.019831367923567694
    },
    "CDD": {
        "error": 1.7367691397937825e-05,
        "error_type": "SEM",
        "filter_outliers_dict": {
            "filter_outliers": true,
            "iterations": 1,
            "std_devs": 10,
            "use_iqr_filtering": false,
            "use_standard_deviation_filtering": false
        },
        "fit": "average",
        "fn": 24,
        "include_baseline_error": false,
        "n": 24,
        "outlier_excluded": [],
        "reviewed": true,
        "user_excluded": [],
        "value": 4.5117581976228394e-05
    },
    "H1": {
        "error": 0.009812281875224179,
        "error_type": "SEM",
        "filter_outliers_dict": {
            "filter_outliers": true,
            "iterations": 1,
            "std_devs": 3,
            "use_iqr_filtering": false,
            "use_standard_deviation_filtering": false
        },
        "fit": "average",
        "fn": 24,
        "include_baseline_error": false,
        "n": 24,
        "outlier_excluded": [],
        "reviewed": true,
        "user_excluded": [],
        "value": 0.006832502467053321
    },
    "H2": {
        "error": 0.04855220384253713,
        "error_type": "SEM",
        "filter_outliers_dict": {
            "filter_outliers": true,
            "iterations": 1,
            "std_devs": 3,
            "use_iqr_filtering": false,
            "use_standard_deviation_filtering": false
        },
        "fit": "average",
        "fn": 24,
        "include_baseline_error": false,
        "n": 24,
        "outlier_excluded": [],
        "reviewed": true,
        "user_excluded": [],
        "value": -0.18170148444672427
    },
    "L1": {
        "error": 0.004512722144653849,
        "error_type": "SEM",
        "filter_outliers_dict": {
            "filter_outliers": true,
            "iterations": 1,
            "std_devs": 3,
            "use_iqr_filtering": false,
            "use_standard_deviation_filtering": false
        },
        "fit": "average",
        "fn": 24,
        "include_baseline_error": false,
        "n": 24,
        "outlier_excluded": [],
        "reviewed": true,
        "user_excluded": [],
        "value": 0.04172929898913935
    },
    "L2": {
        "error": 0.0045012717337861285,
        "error_type": "SEM",
        "filter_outliers_dict": {
            "filter_outliers": true,
            "iterations": 1,
            "std_devs": 3
        },
        "fit": "average",
        "value": -0.03136570923742218
    }
}