{
    "Ar36": {
        "error": 0.0001478456619533218,
        "error_type": "",
        "fit": "previous",
        "references": [
            {
                "exclude": false,
                "record_id": "ba-03-J-969"
            }
        ],
        "value": 0.00425141382129191
    },
    "Ar37": {
        "error": 0.004969170770197421,
        "error_type": "",
        "fit": "previous",
        "references": [
            {
                "exclude": false,
                "record_id": "ba-03-J-969"
            }
        ],
        "value": 0.03685120735776988
    },
    "Ar38": {
        "error": 0.00391727250000249,
        "error_type": "",
        "fit": "previous",
        "references": [
            {
                "exclude": false,
                "record_id": "ba-03-J-969"
            }
        ],
        "value": 0.013836698894488762
    },
    "Ar39": {
        "error": 0.008717246165636046,
        "error_type": "",
        "fit": "previous",
        "references": [
            {
                "exclude": false,
                "record_id": "ba-03-J-969"
            }
        ],
        "value": 0.0909895699173325
    },
    "Ar40": {
        "error": 0.016875011742477516,
        "error_type": "",
        "fit": "previous",
        "references": [
            {
                "exclude": false,
                "record_id": "ba-03-J-969"
            }
        ],
        "value": 0.11114249330134054
    },
    "Ar41": {
        "error": 0.02272242676524075,
        "error_type": "",
        "fit": "previous",
        "references": [
            {
                "exclude": false,
                "record_id": "ba-03-J-969"
            }
        ],
        "value": 0.1926466911228451
    }
}